slitronomy/__init__.py
slitronomy/Lensing/__init__.py
slitronomy/Lensing/lensing_operator.py
slitronomy/Lensing/lensing_plane.py
slitronomy/Optimization/__init__.py
slitronomy/Optimization/algorithms.py
slitronomy/Optimization/model_manager.py
slitronomy/Optimization/model_operators.py
slitronomy/Optimization/noise_levels.py
slitronomy/Optimization/proximals.py
slitronomy/Optimization/solver_base.py
slitronomy/Optimization/solver_lens.py
slitronomy/Optimization/solver_source.py
slitronomy/Optimization/solver_source_alt.py
slitronomy/Optimization/solver_source_lens.py
slitronomy/Optimization/solver_source_ps.py
slitronomy/Util/__init__.py
slitronomy/Util/class_util.py
slitronomy/Util/mask_util.py
slitronomy/Util/metrics_util.py
slitronomy/Util/plot_util.py
slitronomy/Util/solver_plotter.py
slitronomy/Util/solver_tracker.py
slitronomy/Util/util.py
slitronomy-0.3.3.dist-info/LICENSE
slitronomy-0.3.3.dist-info/METADATA
slitronomy-0.3.3.dist-info/WHEEL
slitronomy-0.3.3.dist-info/top_level.txt
slitronomy-0.3.3.dist-info/RECORD
