Metadata-Version: 2.1
Name: slitronomy
Version: 0.3.3
Summary: Sparse Linear Inversion Technique for lenstronomy
Home-page: https://github.com/aymgal/SLITronomy
Author: Aymeric Galan
Author-email: aymeric.galan@gmail.com
License: MIT
Download-URL: https://github.com/aymgal/slitronomy/archive/0.3.2.tar.gz.zip
Keywords: slitronomy
Platform: UNKNOWN
Classifier: Development Status :: 5 - Production/Stable
Classifier: Intended Audience :: Science/Research
Classifier: Natural Language :: English
Classifier: Operating System :: OS Independent
Classifier: Programming Language :: Python
Classifier: Programming Language :: Python :: 3.6
Classifier: Programming Language :: Python :: 3.7
Requires-Python: >=3.6
License-File: LICENSE
Requires-Dist: configparser
